avocado/__init__.py
avocado/__init__.pyi
avocado/py.typed
avocado/logging/__init__.py
avocado/logging/__init__.pyi
avocado/logging/_handler.py
avocado/logging/_init.py
avocado/logging/_timer.py
avocado/logging/once.py
avocado/serde/__init__.py
avocado/serde/__init__.pyi
avocado/serde/_json.py
avocado/serde/_pydantic.py
avocado/serde/_serde.py
avocado/serde/_toml.py
avocado/serde/_yaml.py
avocado/text/__init__.py
avocado/text/__init__.pyi
avocado/text/_strip_comments.py
avocado/typing/__init__.py
avocado/typing/__init__.pyi
avocado/typing/_is_iterable.py
avocado/typing/_is_sequence.py
avocado/typing/_types.py
liblaf_avocado-0.1.1.dist-info/METADATA
liblaf_avocado-0.1.1.dist-info/WHEEL
liblaf_avocado-0.1.1.dist-info/licenses/LICENSE
liblaf_avocado-0.1.1.dist-info/RECORD
